Metadata-Version: 1.0
Name: bng-distributions-prob
Version: 1.1
Summary: Binomial and Gausssian distribution
Home-page: UNKNOWN
Author: Mudassir Ahmed
Author-email: mudassir.ahmed082@gmail.com
License: UNKNOWN
Platform: UNKNOWN
